mcpcc/__init__.py
mcpcc-0.1.4.dist-info/WHEEL
mcpcc-0.1.4.dist-info/entry_points.txt
mcpcc-0.1.4.dist-info/METADATA
mcpcc-0.1.4.dist-info/RECORD
