Metadata-Version: 2.3
Name: mcpcc
Version: 0.1.4
Summary: Add your description here
Author: liujingjing
Author-email: liujingjing <>
Requires-Dist: mcp[cli]>=1.12.3
Requires-Dist: openpyxl>=3.1.5
Requires-Dist: pandas>=2.3.1
Requires-Dist: requests>=2.32.4
Requires-Python: >=3.13
